examples/__init__.py
iSeaborn/__init__.py
iSeaborn/algorithms.py
iSeaborn/axisgrid.py
iSeaborn/categorical.py
iSeaborn/palettes.py
iSeaborn/utils.py
iSeaborn/colors/__init__.py
iSeaborn/colors/crayons.py
iSeaborn/colors/xkcd_rgb.py
iSeaborn/external/__init__.py
iSeaborn/external/husl.py
iSeaborn/external/six.py
iSeaborn/tests/__init__.py
testing/__init__.py
testing/test_bokeh/__init__.py
testing/test_bokeh/testBarplot.py
testing/test_bokeh/testBarplot2.py
testing/test_iSeaborn/__init__.py
testing/test_iSeaborn/testBarplot.py
testing/test_seaborn/__init__.py
testing/test_seaborn/testBarplot.py
iSeaborn-0.0.1.dev0.dist-info/LICENSE
iSeaborn-0.0.1.dev0.dist-info/METADATA
iSeaborn-0.0.1.dev0.dist-info/WHEEL
iSeaborn-0.0.1.dev0.dist-info/top_level.txt
iSeaborn-0.0.1.dev0.dist-info/RECORD
